sphinx_theme_shiratama/.gitignore
sphinx_theme_shiratama/__init__.py
sphinx_theme_shiratama/base.html
sphinx_theme_shiratama/genindex.html
sphinx_theme_shiratama/page.html
sphinx_theme_shiratama/search.html
sphinx_theme_shiratama/theme.conf
sphinx_theme_shiratama/partials/brand.html
sphinx_theme_shiratama/partials/footer.html
sphinx_theme_shiratama/partials/icons.html
sphinx_theme_shiratama/partials/mobile-header.html
sphinx_theme_shiratama/partials/related-pages.html
sphinx_theme_shiratama/partials/search.html
sphinx_theme_shiratama/static/.gitignore
sphinx_theme_shiratama/static/styles/theme.css
sphinx_theme_shiratama-0.1.4.dist-info/entry_points.txt
sphinx_theme_shiratama-0.1.4.dist-info/LICENSE
sphinx_theme_shiratama-0.1.4.dist-info/WHEEL
sphinx_theme_shiratama-0.1.4.dist-info/METADATA
sphinx_theme_shiratama-0.1.4.dist-info/RECORD
