Metadata-Version: 2.3
Name: sphinx-theme-shiratama
Version: 0.1.4
Summary: A simple sphinx theme 
Author: yamabiko
Requires-Python: >=3.8
Classifier: Development Status :: 4 - Beta
Classifier: Framework :: Sphinx :: Theme
Classifier: Programming Language :: Python
Classifier: Programming Language :: Python :: 3
Classifier: License :: OSI Approved :: BSD License
Classifier: Topic :: Documentation
Classifier: Topic :: Software Development :: Documentation
Requires-Dist: sphinx >= 4.2
Requires-Dist: beautifulsoup4
